hdfdict/__init__.py
hdfdict/hdfdict.py
hdfdict-0.3.1.dist-info/LICENSE
hdfdict-0.3.1.dist-info/WHEEL
hdfdict-0.3.1.dist-info/METADATA
hdfdict-0.3.1.dist-info/RECORD
