Metadata-Version: 2.1
Name: hdfdict
Version: 0.3.1
Summary: Helps h5py to load and dump dictionaries containing types supported by h5py.
Home-page: https://github.com/SiggiGue/hdfdict
License: MIT
Author: Siegfried Gündert
Author-email: siegfried.guendert@googlemail.com
Requires-Python: >=3.7,<4.0
Classifier: License :: OSI Approved :: MIT License
Classifier: Programming Language :: Python :: 3
Classifier: Programming Language :: Python :: 3.7
Requires-Dist: h5py-wrapper (>=1.1,<2.0)
Requires-Dist: pyyaml (>=5.1,<6.0)
Project-URL: Repository, https://github.com/SiggiGue/hdfdict
